MANIFEST.in
README-public.md
README.md
README.rst
requirements-common.txt
requirements.txt
setup.cfg
setup.py
common/__init__.py
common/alchemy_instrumentation.py
common/consts.py
common/plan_collect_type.py
common/version.py
common/exporters/__init__.py
common/exporters/file_exporter.py
common/exporters/remote_exporter.py
common/instrumentations/__init__.py
common/instrumentations/consts.py
common/instrumentations/dummy.py
common/instrumentations/instrumentation_config.py
common/utils/__init__.py
common/utils/chunk.py
common/utils/env_var.py
common/utils/log.py
common/utils/once.py
common/utils/singleton_class.py
sqlalchemycollector/__init__.py
sqlalchemycollector/instruments.py
sqlalchemycollector.egg-info/PKG-INFO
sqlalchemycollector.egg-info/SOURCES.txt
sqlalchemycollector.egg-info/dependency_links.txt
sqlalchemycollector.egg-info/requires.txt
sqlalchemycollector.egg-info/top_level.txt