Metadata-Version: 2.1
Name: sqlalchemycollector
Version: 1.4.2
Summary: Metis log collector for Flask and SQLAlchemy
Home-page: https://github.com/metis-data/metis-python-collectors
Author: Metis dev
Author-email: devops@metisdata.io
License: UNKNOWN
Project-URL: Bug Tracker, https://github.com/metis-data/metis-python-collectors/issues
Platform: UNKNOWN
